__init__.py
cadence_detector/CadenceDetectData.py
cadence_detector/CadenceDetectStateMachine.py
cadence_detector/CadenceDetector.py
cadence_detector/__init__.py
cadence_detector/cadence_detector.py
cadence_detector-0.3.0.dist-info/LICENSE
cadence_detector-0.3.0.dist-info/METADATA
cadence_detector-0.3.0.dist-info/WHEEL
cadence_detector-0.3.0.dist-info/top_level.txt
cadence_detector-0.3.0.dist-info/RECORD
