Metadata-Version: 2.1
Name: cadence_detector
Version: 0.3.0
Summary: A python package for cadence detection
Author-email: Matan Ben-Asher <mbenasher@yahoo.com>
Project-URL: Homepage, https://github.com/MusicalStateMachines/CadenceDetector
Project-URL: Bug Tracker, https://github.com/MusicalStateMachines/CadenceDetector/issues
Classifier: Programming Language :: Python :: 3
Classifier: License :: OSI Approved :: MIT License
Classifier: Operating System :: OS Independent
Requires-Python: >=3.9
License-File: LICENSE
Requires-Dist: music21
Requires-Dist: numpy
Requires-Dist: pandas
Requires-Dist: tqdm
